readyperfectly_sample_package/__init__.py
readyperfectly_sample_package/example.py
readyperfectly_sample_package-1.0.37.dist-info/METADATA
readyperfectly_sample_package-1.0.37.dist-info/WHEEL
readyperfectly_sample_package-1.0.37.dist-info/licenses/LICENSE
readyperfectly_sample_package-1.0.37.dist-info/RECORD
