Metadata-Version: 2.4
Name: readyperfectly_sample_package
Version: 1.0.37
Summary: Sample to demostrate writing Python packages
Project-URL: Homepage, https://github.com/ongzhixian/sample-pypi-package/wiki
Project-URL: Issues, https://github.com/ongzhixian/sample-pypi-package/issues
Author-email: Ong Zhi Xian <zhixian@hotmail.com>
License-Expression: MIT
License-File: LICENSE
Classifier: Operating System :: OS Independent
Classifier: Programming Language :: Python :: 3
Requires-Python: >=3.10
